LICENSE
MANIFEST.in
README.md
requirements.txt
setup.py
clquery/__init__.py
clquery/clconfig.py
clquery/schema.py
clquery/shell.py
clquery/table_registry.py
clquery/tables_aws.py
clquery/vtable.py
clquery.egg-info/PKG-INFO
clquery.egg-info/SOURCES.txt
clquery.egg-info/dependency_links.txt
clquery.egg-info/entry_points.txt
clquery.egg-info/requires.txt
clquery.egg-info/top_level.txt
test/test_aws.py
test/test_table_registry.py
test/test_vtable.py